{
  "help": "⚠ Список команд бота ⚠ \n\n /помощь - показать это сообщение 🎉 \n /привет - выводит сообщение для приветствия 😊 \n /кик @упоминание - выкидывает пользователя из чата 😏 \n /бан @упоминание - выкидывает пользователя из чата с концами \n /разбан <ник или id> - разбанивает пользователя и возвращает его обратно в чат (если в друзьях есть бот)",
  "hello": "Ну приветик! Чего хочешь? ;)",
  "unknown": "Мне такая команда неизвестна :C",
  "kick": "КИКАЛИТИ 😏",
  "ban": "БАНАЛИТИ 😏",
  "ban_user": "Привет! Тебя забанили, но если хочешь в дальнейшем вернуться, то добавь меня :3",
  "return_user": "С возвращением, проказник!",
  "return": "Пользователь разбанен, теперь вы можете вернуть его в беседу"
}
